coif/__init__.py
coif/coif.py
coif-0.0.1.dist-info/LICENSE
coif-0.0.1.dist-info/METADATA
coif-0.0.1.dist-info/WHEEL
coif-0.0.1.dist-info/top_level.txt
coif-0.0.1.dist-info/RECORD
