Metadata-Version: 2.1
Name: coif
Version: 0.0.1
Summary: Cover image finder: find a cover image given a book identifier
Home-page: https://github.com/caltechlibrary/coif
Author: Michael Hucka
Author-email: mhucka@caltech.edu
License: BSD 3-clause
Project-URL: Source Code, https://github.com/caltechlibrary/coif
Project-URL: Bug Tracker, https://github.com/caltechlibrary/coif/issues
Keywords: Python,utilities
Platform: UNKNOWN
Classifier: Development Status :: 3 - Alpha
Classifier: Intended Audience :: Science/Research
Classifier: License :: OSI Approved :: BSD License
Classifier: Operating System :: MacOS :: MacOS X
Classifier: Operating System :: Microsoft :: Windows
Classifier: Operating System :: POSIX
Classifier: Operating System :: POSIX :: Linux
Classifier: Operating System :: Unix
Classifier: Programming Language :: Python
Classifier: Programming Language :: Python :: 3.6
Requires-Python: >=3.6
License-File: LICENSE
Requires-Dist: commonpy (>=1.3.10)
Requires-Dist: sidetrack (>=2.0.0)
